setup.py
skyCurses/__init__.py
skyCurses/_audio_wrapper.py
skyCurses/_mplayer_wrapper.py
skyCurses/alias.json
skyCurses/skyCurses.py
skyCurses.egg-info/PKG-INFO
skyCurses.egg-info/SOURCES.txt
skyCurses.egg-info/dependency_links.txt
skyCurses.egg-info/entry_points.txt
skyCurses.egg-info/not-zip-safe
skyCurses.egg-info/requires.txt
skyCurses.egg-info/top_level.txt
skyCurses/sounds/end.wav
skyCurses/sounds/mp.wav
skyCurses/sounds/msg.wav
skyCurses/sounds/nomi.wav