Metadata-Version: 1.0
Name: skyCurses
Version: 2.0.13.post3
Summary: Unofficial curses client for the SkyChat
Home-page: http://git.beerstorm.info/Beerstorm/SkyCurses
Author: Beerstorm
Author-email: beerstorm.emberbeard@gmail.com
License: GPLv3
Platform: UNKNOWN
